django_json_logging/__init__.py
django_json_logging/formatters.py
django_json_logging/serializers.py
django_json_logging/settings.py
django_json_logger-0.1.1.dist-info/LICENSE
django_json_logger-0.1.1.dist-info/METADATA
django_json_logger-0.1.1.dist-info/WHEEL
django_json_logger-0.1.1.dist-info/top_level.txt
django_json_logger-0.1.1.dist-info/RECORD
