Metadata-Version: 2.2
Name: django-json-logger
Version: 0.1.1
Summary: A Django app to logging in json format.
Author-email: Maksim Kopytov <misst3rr@gmail.com>
License: Copyright 2023 Maksim Kopytov
Project-URL: Homepage, https://github.com/missterr/django-json-logging
Classifier: License :: Freeware
Classifier: Framework :: Django
Classifier: Framework :: Django :: 3.0
Classifier: Framework :: Django :: 3.1
Classifier: Framework :: Django :: 3.2
Classifier: Framework :: Django :: 4
Classifier: Framework :: Django :: 4.1
Classifier: Framework :: Django :: 4.2
Classifier: Intended Audience :: Developers
Classifier: Operating System :: OS Independent
Classifier: Programming Language :: Python
Classifier: Programming Language :: Python :: 3.8
Classifier: Programming Language :: Python :: 3.9
Classifier: Programming Language :: Python :: 3.10
Requires-Python: >=3.8
License-File: LICENSE
Requires-Dist: django>=3.0
Provides-Extra: dev
Requires-Dist: black; extra == "dev"
Requires-Dist: isort; extra == "dev"
Requires-Dist: orjson; extra == "dev"
Requires-Dist: ujson; extra == "dev"
Provides-Extra: orjson
Requires-Dist: orjson>=3.4.3; extra == "orjson"
Provides-Extra: ujson
Requires-Dist: ujson>=4.2.0; extra == "ujson"
